bioutils/__init__.py
bioutils/_versionwarning.py
bioutils/accessions.py
bioutils/assemblies.py
bioutils/coordinates.py
bioutils/cytobands.py
bioutils/digest.py
bioutils/digests.py
bioutils/exceptions.py
bioutils/normalize.py
bioutils/seqfetcher.py
bioutils/sequences.py
bioutils/vmc_digest.py
bioutils/_data/assemblies/.gitignore
bioutils/_data/assemblies/CHM1_1.0.json.gz
bioutils/_data/assemblies/CHM1_1.1.json.gz
bioutils/_data/assemblies/GRCh37.json.gz
bioutils/_data/assemblies/GRCh37.p10.json.gz
bioutils/_data/assemblies/GRCh37.p11.json.gz
bioutils/_data/assemblies/GRCh37.p12.json.gz
bioutils/_data/assemblies/GRCh37.p13.json.gz
bioutils/_data/assemblies/GRCh37.p2.json.gz
bioutils/_data/assemblies/GRCh37.p5.json.gz
bioutils/_data/assemblies/GRCh37.p9.json.gz
bioutils/_data/assemblies/GRCh38.json.gz
bioutils/_data/assemblies/GRCh38.p1.json.gz
bioutils/_data/assemblies/GRCh38.p10.json.gz
bioutils/_data/assemblies/GRCh38.p11.json.gz
bioutils/_data/assemblies/GRCh38.p12.json.gz
bioutils/_data/assemblies/GRCh38.p13.json.gz
bioutils/_data/assemblies/GRCh38.p14.json.gz
bioutils/_data/assemblies/GRCh38.p2.json.gz
bioutils/_data/assemblies/GRCh38.p3.json.gz
bioutils/_data/assemblies/GRCh38.p4.json.gz
bioutils/_data/assemblies/GRCh38.p5.json.gz
bioutils/_data/assemblies/GRCh38.p6.json.gz
bioutils/_data/assemblies/GRCh38.p7.json.gz
bioutils/_data/assemblies/GRCh38.p8.json.gz
bioutils/_data/assemblies/GRCh38.p9.json.gz
bioutils/_data/assemblies/Makefile
bioutils/_data/assemblies/NCBI33.json.gz
bioutils/_data/assemblies/NCBI34.json.gz
bioutils/_data/assemblies/NCBI35.json.gz
bioutils/_data/assemblies/NCBI36.json.gz
bioutils/_data/assemblies/T2T-CHM13v2.0.json.gz
bioutils/_data/cytobands/ucsc-hg19.json.gz
bioutils/_data/cytobands/ucsc-hg38.json.gz
bioutils-0.6.1.dist-info/LICENSE.txt
bioutils-0.6.1.dist-info/METADATA
bioutils-0.6.1.dist-info/WHEEL
bioutils-0.6.1.dist-info/top_level.txt
bioutils-0.6.1.dist-info/RECORD
