Metadata-Version: 2.1
Name: bioutils
Version: 0.6.1
Summary: miscellaneous simple bioinformatics utilities and lookup tables
Author-email: biocommons contributors <biocommons-dev@googlegroups.com>
License:                                  Apache License
Project-URL: Homepage, https://github.com/biocommons/bioutils
Project-URL: Bug Tracker, https://github.com/biocommons/bioutils/issues
Keywords: biocommons,bioinformatics,genomics,HGVS,variation
Classifier: Programming Language :: Python :: 3
Classifier: Programming Language :: Python :: 3.10
Classifier: Programming Language :: Python :: 3.11
Classifier: Programming Language :: Python :: 3.12
Classifier: License :: OSI Approved :: Apache Software License
Classifier: Operating System :: OS Independent
Classifier: Topic :: Scientific/Engineering :: Bio-Informatics
Classifier: Topic :: Scientific/Engineering :: Medical Science Apps.
Requires-Python: >=3.10
License-File: LICENSE.txt
Requires-Dist: attrs
Requires-Dist: requests
Provides-Extra: dev
Requires-Dist: bandit~=1.7; extra == "dev"
Requires-Dist: build~=0.8; extra == "dev"
Requires-Dist: flake8~=4.0; extra == "dev"
Requires-Dist: ipython~=8.4; extra == "dev"
Requires-Dist: isort~=5.10; extra == "dev"
Requires-Dist: mypy; extra == "dev"
Requires-Dist: pylint~=2.14; extra == "dev"
Requires-Dist: ruff==0.4.4; extra == "dev"
Provides-Extra: test
Requires-Dist: pytest~=7.1; extra == "test"
Requires-Dist: pytest-cov~=4.0; extra == "test"
Requires-Dist: pytest-optional-tests; extra == "test"
Requires-Dist: tox~=3.25; extra == "test"
Requires-Dist: vcrpy; extra == "test"
Provides-Extra: docs
Requires-Dist: mkdocs; extra == "docs"
